README.md
monpyou_demo
setup.py
monpyou/__init__.py
monpyou.egg-info/PKG-INFO
monpyou.egg-info/SOURCES.txt
monpyou.egg-info/dependency_links.txt
monpyou.egg-info/not-zip-safe
monpyou.egg-info/requires.txt
monpyou.egg-info/top_level.txt
test/__init__.py
test/test_parsing.py