Metadata-Version: 2.1
Name: monpyou
Version: 0.1.1
Summary: Python library to read account information from moneyou bank.
Home-page: https://github.com/christian.kuehnel/monpyou
Author: Christian Kühnel
Author-email: christian.kuehnel@gmail.com
License: Apache 2.0
Keywords: Moneyou banking
Platform: UNKNOWN
Classifier: Development Status :: 4 - Beta
Classifier: Intended Audience :: Developers
Classifier: License :: OSI Approved :: MIT License
Classifier: Programming Language :: Python :: 3
Classifier: Programming Language :: Python :: 3.4
Classifier: Programming Language :: Python :: 3.5
Classifier: Programming Language :: Python :: 3.6
Provides-Extra: testing
